dcolumn/__init__.py
dcolumn/common/__init__.py
dcolumn/common/admin_mixins.py
dcolumn/common/choice_mixins.py
dcolumn/common/decorators.py
dcolumn/common/model_mixins.py
dcolumn/common/view_mixins.py
dcolumn/dcolumns/__init__.py
dcolumn/dcolumns/admin.py
dcolumn/dcolumns/forms.py
dcolumn/dcolumns/manager.py
dcolumn/dcolumns/models.py
dcolumn/dcolumns/urls.py
dcolumn/dcolumns/views.py
dcolumn/dcolumns/migrations/0001_initial.py
dcolumn/dcolumns/migrations/0002_auto_20160130_1715.py
dcolumn/dcolumns/migrations/0003_auto_20160308_2158.py
dcolumn/dcolumns/migrations/0004_columncollection_related_model.py
dcolumn/dcolumns/migrations/0005_auto_20160906_1706.py
dcolumn/dcolumns/migrations/0006_auto_20160906_1920.py
dcolumn/dcolumns/migrations/0007_auto_20210518_1424.py
dcolumn/dcolumns/migrations/__init__.py
dcolumn/dcolumns/static/dcolumn/css/column-collection.css
dcolumn/dcolumns/static/dcolumn/js/column-collection.js
dcolumn/dcolumns/static/dcolumn/js/dynamic-column.js
dcolumn/dcolumns/static/dcolumn/js/inheritance.js
dcolumn/dcolumns/static/dcolumn/js/js.cookie-2.0.4.js
dcolumn/dcolumns/static/dcolumn/js/js.cookie-2.0.4.min.js
dcolumn/dcolumns/templatetags/__init__.py
dcolumn/dcolumns/templatetags/autodisplay.py
django_dcolumns-3.1.0.dist-info/LICENSE.txt
django_dcolumns-3.1.0.dist-info/METADATA
django_dcolumns-3.1.0.dist-info/WHEEL
django_dcolumns-3.1.0.dist-info/top_level.txt
django_dcolumns-3.1.0.dist-info/RECORD
