Metadata-Version: 2.1
Name: django-dcolumns
Version: 3.1.0
Summary: An app to give any Django database model the ability to dynamically add fields.
Home-page: https://github.com/cnobile2012/dcolumn
Author: Carl J. Nobile
Author-email: carl.nobile@gmail.com
License: MIT
Project-URL: Source, https://github.com/cnobile2012/dcolumn
Keywords: Django DColumns
Platform: UNKNOWN
Classifier: Environment :: Web Environment
Classifier: Framework :: Django
Classifier: Intended Audience :: Developers
Classifier: License :: OSI Approved :: MIT License
Classifier: Operating System :: OS Independent
Classifier: Programming Language :: Python
Classifier: Programming Language :: Python :: 3
Classifier: Programming Language :: Python :: 3.5
Classifier: Programming Language :: Python :: 3.6
Classifier: Programming Language :: Python :: 3.7
Classifier: Topic :: Software Development :: Build Tools
Classifier: Topic :: Internet :: WWW/HTTP
Classifier: Topic :: Internet :: WWW/HTTP :: Dynamic Content
Requires-Dist: django
Requires-Dist: dateutils
Requires-Dist: python-dateutil
